{"Stim Packs":{"id":0},"Lockdown":{"id":1},"EMP Shockwave":{"id":2},"Spider Mines":{"id":3},"Scanner Sweep":{"id":4},"Tank Siege Mode":{"id":5},"Defensive Matrix":{"id":6},"Irradiate":{"id":7},"Yamato Gun":{"id":8},"Cloaking Field":{"id":9},"Personnel Cloaking":{"id":10},"Burrowing":{"id":11},"Infestation":{"id":12},"Spawn Broodlings":{"id":13},"Dark Swarm":{"id":14},"Plague":{"id":15},"Consume":{"id":16},"Ensnare":{"id":17},"Parasite":{"id":18},"Psionic Storm":{"id":19},"Hallucination":{"id":20},"Recall":{"id":21},"Stasis Field":{"id":22},"Archon Warp":{"id":23},"Restoration":{"id":24},"Disruption Web":{"id":25},"Unknown Tech26":{"id":26},"Mind Control":{"id":27},"Dark Archon Meld":{"id":28},"Feedback":{"id":29},"Optical Flare":{"id":30},"Maelstorm":{"id":31},"Lurker Aspect":{"id":32},"Unknown Tech33":{"id":33},"Healing":{"id":34},"Unknown Tech35":{"id":35},"Unknown Tech36":{"id":36},"Unknown Tech37":{"id":37},"Unknown Tech38":{"id":38},"Unknown Tech39":{"id":39},"Unknown Tech40":{"id":40},"Unknown Tech41":{"id":41},"Unknown Tech42":{"id":42},"Unknown Tech43":{"id":43},"None":{"id":44}}